<?xml version="1.0"?>
<!DOCTYPE hibernate-mapping PUBLIC
        "-//Hibernate/Hibernate Mapping DTD 3.0//EN"
        "http://hibernate.sourceforge.net/hibernate-mapping-3.0.dtd">

<hibernate-mapping default-lazy="false"> 
  <class name="gov.epa.emissions.framework.services.cost.ControlStrategy" table="control_strategies" schema="emf"> 
 	<id name="id" type="integer" column="id">
	  <generator class="identity"/>
 	</id>
	<property name="name" column="name"	type="java.lang.String"	not-null="true"/>
	<property name="description" column="description" type="java.lang.String"/>
	<property name="runStatus" column="run_status"	type="java.lang.String"/>
	<property name="discountRate" column="discount_rate" type="double"/>
	<property name="costYear" column="cost_year" type="integer" not-null="false"/>
	<property name="analysisYear" column="analysis_year" type="integer" not-null="false"/>
	<property name="lastModifiedDate" column="last_modified_date" type="java.util.Date" not-null="false" length="4"/>
  	<property name="startDate" column="start_date" type="java.util.Date" not-null="false" length="4"/>
  	<property name="completionDate" column="completion_date" type="java.util.Date" not-null="false" length="4"/>
	<property name="datasetVersion" column="dataset_version" type="integer" not-null="true"/>
	<property name="targetPollutant" column="target_pollutant" type="java.lang.String"/>
	<property name="lockOwner" column="lock_owner" type="java.lang.String" not-null="false"/>
  	<property name="lockDate" column="lock_date" type="java.util.Date" not-null="false" length="4"/>
		
	<many-to-one cascade="save-update"
            name="region" 
            class="gov.epa.emissions.commons.data.Region"
            column="region_id"/> 
            
	<many-to-one cascade="save-update"
            name="project" 
            class="gov.epa.emissions.commons.data.Project"
            column="project_id"/> 

	<many-to-one cascade="save-update"
            name="creator" 
            class="gov.epa.emissions.commons.security.User"
            column="creator_id"/> 
            
	<many-to-one cascade="save-update"
            name="datasetType" 
            class="gov.epa.emissions.commons.data.DatasetType"
            column="dataset_type_id"/> 

	<many-to-one cascade="save-update"
            name="strategyType" 
            class="gov.epa.emissions.framework.services.cost.StrategyType"
            column="strategy_type_id"/> 
            
   	<array name="inputDatasets" table="input_datasets_control_strategies" >
    	<key column="control_strategy_id" not-null="true"/>
	    <list-index column="list_index"/>
    	<many-to-many class="gov.epa.emissions.framework.services.data.EmfDataset" column="dataset_id"/>
	</array>
	
	<array name="strategyResults" table="strategy_results" >
    	<key column="control_strategy_id" not-null="true"/>
    	<list-index column="list_index"/>
    	<composite-element class="gov.epa.emissions.framework.services.cost.controlStrategy.StrategyResult">
			<property name="inputDatasetId" column="dataset_id" />
			<property name="totalCost" column="total_cost" not-null="true"/>
			<property name="totalReduction" column="total_reduction" type="double"  not-null="true" />
			<property name="runStatus" column="run_status"	type="java.lang.String"	/>
			<property name="completionTime" column="completion_time" type="java.util.Date" not-null="false" length="4"/>
			<many-to-one cascade="save-update" name="strategyResultType"
				 class ="gov.epa.emissions.framework.services.cost.controlStrategy.StrategyResultType"
				 column="strategy_result_type_id" unique="true" not-null="true"/>
			<many-to-one cascade="save-update" name="detailedResultDataset"
				 class ="gov.epa.emissions.framework.services.data.EmfDataset"
				 column="detailed_result_dataset_id" unique="true" not-null="true"/>
    	</composite-element>
  	</array>
	
  </class> 
</hibernate-mapping>  
